cosolvkit/__init__.py
cosolvkit/analysis.py
cosolvkit/config.py
cosolvkit/cosolvent_system.py
cosolvkit/simulation.py
cosolvkit/utils.py
cosolvkit/cli/__init__.py
cosolvkit/cli/create_cosolvent_system.py
cosolvkit/cli/post_simulation_processing.py
cosolvkit/data/aa.json
cosolvkit/data/aromatic.json
cosolvkit/data/config.json
cosolvkit/data/cosolvents.json
cosolvkit/data/forcefields.json
cosolvkit/data/h_bonding.json
cosolvkit/data/lipophilic.json
cosolvkit/data/negative.json
cosolvkit/data/positive.json
cosolvkit-0.5.0.dist-info/LICENSE
cosolvkit-0.5.0.dist-info/METADATA
cosolvkit-0.5.0.dist-info/WHEEL
cosolvkit-0.5.0.dist-info/entry_points.txt
cosolvkit-0.5.0.dist-info/top_level.txt
cosolvkit-0.5.0.dist-info/RECORD
