Metadata-Version: 2.1
Name: cosolvkit
Version: 0.5.0
Summary: CosolvKit
Home-page: https://github.com/forlilab/cosolvkit
Author: Niccolo Bruciaferri, Jerome Eberhardt
Author-email: forli@scripps.edu
License: LGPL-2.1
Keywords: molecular modeling,drug design,cosolvent,MD simulations
Classifier: Programming Language :: Python
Classifier: Operating System :: Unix
Classifier: Operating System :: MacOS
Classifier: Topic :: Scientific/Engineering
License-File: LICENSE
